utilsovs/__init__.py
utilsovs/commons.py
utilsovs/compute.py
utilsovs/draw.py
utilsovs/globals.py
utilsovs/glygen.py
utilsovs/main.py
utilsovs/models.py
utilsovs/oglcnacDB.py
utilsovs/prepare.py
utilsovs/proteome.py
utilsovs/pubmed.py
utilsovs/semantic.py
utilsovs/uniprot.py
utilsovs_pkg-0.9.5.dist-info/LICENSE
utilsovs_pkg-0.9.5.dist-info/METADATA
utilsovs_pkg-0.9.5.dist-info/WHEEL
utilsovs_pkg-0.9.5.dist-info/top_level.txt
utilsovs_pkg-0.9.5.dist-info/RECORD
