Metadata-Version: 2.1
Name: utilsovs-pkg
Version: 0.9.5
Summary: Utils derived from the O-GlcNAc Database source code
Home-page: https://github.com/synthaze/utilsovs
Author: Florian Malard, PhD
Author-email: florian.malard@gmail.com
License: UNKNOWN
Project-URL: Bug Tracker, https://github.com/synthaze/utilsovs/issues
Platform: UNKNOWN
Classifier: Programming Language :: Python :: 3
Classifier: License :: OSI Approved :: GNU General Public License v3 (GPLv3)
Classifier: Operating System :: OS Independent
Requires-Python: >=3.7
License-File: LICENSE
Requires-Dist: Bio (==1.3.3)
Requires-Dist: logomaker (==0.8)
Requires-Dist: matplotlib (==3.5.1)
Requires-Dist: pandas (==1.3.5)
Requires-Dist: Pygments (==2.7.1)
Requires-Dist: requests (==2.25.1)
Requires-Dist: tika (==1.24)
Requires-Dist: wget (==3.2)
